mtd_parser/__init__.py
mtd_parser/__main__.py
mtd_parser/exceptions.py
mtd_parser/log.conf
mtd_parser/method.peg
mtd_parser/method_parser.py
mtd_parser/method_visitor.py
mtd_parser-0.2.2.dist-info/licenses/LICENSE
mtd_parser-0.2.2.dist-info/METADATA
mtd_parser-0.2.2.dist-info/WHEEL
mtd_parser-0.2.2.dist-info/entry_points.txt
mtd_parser-0.2.2.dist-info/top_level.txt
mtd_parser-0.2.2.dist-info/RECORD
