Metadata-Version: 2.4
Name: mtd-parser
Version: 0.2.2
Summary: Executable Shlaer-Mellor Class Method Parser
Author-email: Leon Starr <leon_starr@modelint.com>
License: MIT License
Project-URL: repository, https://github.com/modelint/mtd-parser
Project-URL: documentation, https://github.com/modelint/mtd-parser/wiki
Keywords: action language,executable uml,method,class method,mbse,xuml,xtuml,platform independent,sysml
Classifier: License :: OSI Approved :: MIT License
Classifier: Programming Language :: Python
Classifier: Programming Language :: Python :: 3
Requires-Python: >=3.11
License-File: LICENSE
Requires-Dist: Arpeggio
Requires-Dist: tomli; python_version < "3.11"
Provides-Extra: build
Requires-Dist: build; extra == "build"
Requires-Dist: twine; extra == "build"
Provides-Extra: dev
Requires-Dist: bump2version; extra == "dev"
Requires-Dist: pytest; extra == "dev"
Dynamic: license-file
